hookpulse/__init__.py
hookpulse/client.py
hookpulse/exceptions.py
hookpulse-1.0.2.dist-info/METADATA
hookpulse-1.0.2.dist-info/WHEEL
hookpulse-1.0.2.dist-info/top_level.txt
hookpulse-1.0.2.dist-info/RECORD
