Metadata-Version: 2.4
Name: hookpulse
Version: 1.0.2
Summary: Official Python SDK for HookPulse - Enterprise-grade serverless task scheduling and webhook orchestration. Built with Elixir/OTP for 99.9% uptime and millisecond precision.
Home-page: https://hookpulse.io
Author: HookPulse
Author-email: care@hookpulse.io
Project-URL: Documentation, https://docs.hookpulse.io/docs
Project-URL: Source, https://github.com/HookPulse/hookpulse-packages/tree/main/hookpulse-python
Project-URL: Bug Tracker, https://github.com/HookPulse/hookpulse-packages/issues
Project-URL: Support, https://hookpulse.io/contact
Keywords: hookpulse,webhook,scheduling,task-scheduling,cron,api,sdk,python,elixir,otp,celery,redis,sidekiq,background-jobs,webhook-scheduler,task-automation,workflow,serverless,python-sdk,webhook-orchestration,millisecond-precision,enterprise-reliability,fault-tolerance,python-automation,scheduled-tasks,python-cron,python-scheduler
Classifier: Development Status :: 5 - Production/Stable
Classifier: Intended Audience :: Developers
Classifier: Topic :: Software Development :: Libraries :: Python Modules
Classifier: Topic :: Internet :: WWW/HTTP
Classifier: License :: OSI Approved :: MIT License
Classifier: Programming Language :: Python :: 3
Classifier: Programming Language :: Python :: 3.7
Classifier: Programming Language :: Python :: 3.8
Classifier: Programming Language :: Python :: 3.9
Classifier: Programming Language :: Python :: 3.10
Classifier: Programming Language :: Python :: 3.11
Classifier: Programming Language :: Python :: 3.12
Requires-Python: >=3.7
Requires-Dist: requests>=2.25.0
Provides-Extra: dev
Requires-Dist: pytest>=7.0.0; extra == "dev"
Requires-Dist: pytest-cov>=4.0.0; extra == "dev"
Requires-Dist: black>=23.0.0; extra == "dev"
Requires-Dist: flake8>=6.0.0; extra == "dev"
Requires-Dist: mypy>=1.0.0; extra == "dev"
Dynamic: author
Dynamic: author-email
Dynamic: classifier
Dynamic: description
Dynamic: description-content-type
Dynamic: home-page
Dynamic: keywords
Dynamic: project-url
Dynamic: provides-extra
Dynamic: requires-dist
Dynamic: requires-python
Dynamic: summary
